{
    "name": "syn_1inp_len5_000341",
    "max_cycles": 32,
    "input_ports": [0],
    "output_ports": [0],
    "tests": [
        {"in": [0], "out": [7]},
        {"in": [1], "out": [3]},
        {"in": [56911], "out": [13]},
        {"in": [38664], "out": [1208]},
        {"in": [50962], "out": [1]},
        {"in": [14070], "out": [1758]},
        {"in": [32768], "out": [3]},
        {"in": [25333], "out": [6332]},
        {"in": [10546], "out": [0]},
        {"in": [49680], "out": [6]}
    ]
}
