{
    "name": "syn_2inp_len10_000388",
    "max_cycles": 32,
    "input_ports": [0, 1],
    "output_ports": [0],
    "tests": [
        {"in": [35095, 22362], "out": [34836]},
        {"in": [25003, 20918], "out": [24744]},
        {"in": [40615, 80], "out": [40356]},
        {"in": [45452, 27173], "out": [45193]},
        {"in": [58321, 30156], "out": [58062]},
        {"in": [32, 32767], "out": [65309]},
        {"in": [4, 4], "out": [65281]},
        {"in": [135, 29791], "out": [65412]},
        {"in": [13201, 46440], "out": [12942]},
        {"in": [7907, 50451], "out": [7648]}
    ]
}
