{
    "name": "syn_2inp_len9_000297",
    "max_cycles": 32,
    "input_ports": [0, 1],
    "output_ports": [0],
    "tests": [
        {"in": [19190, 9485], "out": [65535]},
        {"in": [42802, 36745], "out": [65535]},
        {"in": [1725, 22746], "out": [0]},
        {"in": [26777, 32883], "out": [64514]},
        {"in": [256, 3], "out": [65534]},
        {"in": [18520, 54523], "out": [65535]},
        {"in": [43436, 29370], "out": [0]},
        {"in": [16, 16], "out": [0]},
        {"in": [32768, 32768], "out": [0]},
        {"in": [59200, 51278], "out": [65535]}
    ]
}
