{
    "name": "syn_2inp_len7_000334",
    "max_cycles": 32,
    "input_ports": [0, 1],
    "output_ports": [0],
    "tests": [
        {"in": [48658, 51892], "out": [51791]},
        {"in": [1126, 12358], "out": [12477]},
        {"in": [13157, 54453], "out": [54350]},
        {"in": [22023, 56535], "out": [56364]},
        {"in": [128, 1], "out": [65282]},
        {"in": [51449, 11440], "out": [11347]},
        {"in": [32960, 43178], "out": [43097]},
        {"in": [21631, 55406], "out": [55445]},
        {"in": [9701, 34967], "out": [34924]},
        {"in": [47778, 20008], "out": [20187]}
    ]
}
