{
    "name": "syn_2inp_len8_000018",
    "max_cycles": 32,
    "input_ports": [0, 1],
    "output_ports": [0],
    "tests": [
        {"in": [42497, 35397], "out": [23559]},
        {"in": [58553, 30056], "out": [6991]},
        {"in": [6506, 43376], "out": [59040]},
        {"in": [4827, 64108], "out": [60717]},
        {"in": [37070, 36316], "out": [28476]},
        {"in": [63, 63], "out": [65481]},
        {"in": [50249, 9223], "out": [15295]},
        {"in": [20690, 13632], "out": [44872]},
        {"in": [29035, 43703], "out": [36509]},
        {"in": [0, 8], "out": [16]}
    ]
}
