{
    "name": "syn_2inp_len9_000181",
    "max_cycles": 32,
    "input_ports": [0, 1],
    "output_ports": [0],
    "tests": [
        {"in": [12595, 10784], "out": [12592]},
        {"in": [63536, 12336], "out": [63521]},
        {"in": [26908, 37085], "out": [26905]},
        {"in": [48821, 22297], "out": [48818]},
        {"in": [16904, 56132], "out": [16897]},
        {"in": [15396, 53123], "out": [15393]},
        {"in": [41950, 15382], "out": [41945]},
        {"in": [32768, 5], "out": [1]},
        {"in": [2, 16], "out": [1]},
        {"in": [7405, 11245], "out": [7402]}
    ]
}
