{
    "name": "syn_2inp_len6_000293",
    "max_cycles": 32,
    "input_ports": [0, 1],
    "output_ports": [0],
    "tests": [
        {"in": [19357, 56595], "out": [28428]},
        {"in": [49875, 63313], "out": [52228]},
        {"in": [24490, 35916], "out": [54240]},
        {"in": [37530, 24996], "out": [12664]},
        {"in": [32457, 55859], "out": [42264]},
        {"in": [38458, 23130], "out": [15458]},
        {"in": [64, 65535], "out": [195]},
        {"in": [255, 2], "out": [383]},
        {"in": [10794, 42200], "out": [34260]},
        {"in": [53635, 17261], "out": [36504]}
    ]
}
