{
    "name": "syn_2inp_len10_000122",
    "max_cycles": 32,
    "input_ports": [0, 1],
    "output_ports": [0],
    "tests": [
        {"in": [32455, 57085], "out": [40960]},
        {"in": [59523, 54300], "out": [49152]},
        {"in": [56519, 16720], "out": [16752]},
        {"in": [47591, 4708], "out": [9792]},
        {"in": [39661, 33556], "out": [13120]},
        {"in": [50160, 24272], "out": [24304]},
        {"in": [4155, 8318], "out": [32768]},
        {"in": [38309, 16821], "out": [13984]},
        {"in": [4, 32], "out": [32]},
        {"in": [4017, 5635], "out": [45336]}
    ]
}
