{
    "name": "syn_2inp_len10_000188",
    "max_cycles": 32,
    "input_ports": [0, 1],
    "output_ports": [0],
    "tests": [
        {"in": [60729, 54387], "out": [54389]},
        {"in": [17770, 30530], "out": [30532]},
        {"in": [13580, 27925], "out": [27927]},
        {"in": [43461, 25928], "out": [25930]},
        {"in": [26755, 31581], "out": [31583]},
        {"in": [5, 5], "out": [7]},
        {"in": [20743, 57959], "out": [57961]},
        {"in": [22436, 11168], "out": [11170]},
        {"in": [59524, 22682], "out": [22684]},
        {"in": [16387, 31423], "out": [31425]}
    ]
}
