{
    "name": "syn_1inp_len4_000382",
    "max_cycles": 32,
    "input_ports": [0],
    "output_ports": [0],
    "tests": [
        {"in": [0], "out": [65534]},
        {"in": [1], "out": [65533]},
        {"in": [60373], "out": [5161]},
        {"in": [8193], "out": [57341]},
        {"in": [38847], "out": [26687]},
        {"in": [63], "out": [65471]},
        {"in": [59137], "out": [6397]},
        {"in": [51087], "out": [14447]},
        {"in": [28357], "out": [37177]},
        {"in": [32767], "out": [32767]}
    ]
}
