{
    "name": "syn_2inp_len8_000125",
    "max_cycles": 32,
    "input_ports": [0, 1],
    "output_ports": [0],
    "tests": [
        {"in": [14132, 14049], "out": [883]},
        {"in": [27488, 47155], "out": [27488]},
        {"in": [3567, 34202], "out": [0]},
        {"in": [36108, 8227], "out": [8]},
        {"in": [32768, 5], "out": [32768]},
        {"in": [18136, 29182], "out": [70]},
        {"in": [59488, 59007], "out": [59488]},
        {"in": [16576, 17981], "out": [16576]},
        {"in": [3386, 36255], "out": [3]},
        {"in": [32757, 17794], "out": [1023]}
    ]
}
