{
    "name": "syn_2inp_len10_000315",
    "max_cycles": 32,
    "input_ports": [0, 1],
    "output_ports": [0],
    "tests": [
        {"in": [49811, 2889], "out": [543]},
        {"in": [52586, 47106], "out": [4991]},
        {"in": [5654, 24044], "out": [54143]},
        {"in": [40941, 11560], "out": [57887]},
        {"in": [7376, 37647], "out": [61695]},
        {"in": [17570, 11432], "out": [16255]},
        {"in": [21079, 5672], "out": [56607]},
        {"in": [33218, 21839], "out": [12159]},
        {"in": [31, 256], "out": [38687]},
        {"in": [50236, 36570], "out": [20223]}
    ]
}
