{
    "name": "syn_2inp_len4_000024",
    "max_cycles": 32,
    "input_ports": [0, 1],
    "output_ports": [0],
    "tests": [
        {"in": [61967, 22619], "out": [43593]},
        {"in": [32368, 57366], "out": [40549]},
        {"in": [13909, 34078], "out": [45894]},
        {"in": [53974, 9114], "out": [61763]},
        {"in": [52588, 9024], "out": [60975]},
        {"in": [19972, 26387], "out": [10516]},
        {"in": [51509, 23482], "out": [37506]},
        {"in": [4278, 39101], "out": [34820]},
        {"in": [41674, 27643], "out": [51510]},
        {"in": [14132, 12800], "out": [1335]}
    ]
}
