{
    "name": "syn_2inp_len4_000330",
    "max_cycles": 32,
    "input_ports": [0, 1],
    "output_ports": [0],
    "tests": [
        {"in": [18272, 10329], "out": [18274]},
        {"in": [47997, 41864], "out": [7]},
        {"in": [4, 4], "out": [2]},
        {"in": [10, 45079], "out": [2]},
        {"in": [4095, 54408], "out": [2]},
        {"in": [4280, 51108], "out": [18]},
        {"in": [38155, 21289], "out": [20]},
        {"in": [18666, 8886], "out": [20]},
        {"in": [53327, 36927], "out": [3]},
        {"in": [15841, 43515], "out": [7922]}
    ]
}
