{
    "name": "syn_2inp_len2_000368",
    "max_cycles": 32,
    "input_ports": [0, 1],
    "output_ports": [0],
    "tests": [
        {"in": [54962, 24842], "out": [24841]},
        {"in": [2816, 62179], "out": [62178]},
        {"in": [58033, 58754], "out": [58753]},
        {"in": [44145, 21029], "out": [21028]},
        {"in": [51693, 28694], "out": [28693]},
        {"in": [62820, 7439], "out": [7438]},
        {"in": [38004, 38937], "out": [38936]},
        {"in": [39926, 15630], "out": [15629]},
        {"in": [8, 8], "out": [7]},
        {"in": [24149, 48106], "out": [48105]}
    ]
}
