{
    "name": "syn_2inp_len3_000638",
    "max_cycles": 32,
    "input_ports": [0, 1],
    "output_ports": [0],
    "tests": [
        {"in": [45369, 40334], "out": [5035]},
        {"in": [26078, 33952], "out": [49788]},
        {"in": [62786, 37637], "out": [25934]},
        {"in": [7098, 41988], "out": [32561]},
        {"in": [62123, 28782], "out": [33343]},
        {"in": [42247, 27741], "out": [14507]},
        {"in": [56094, 56466], "out": [15919]},
        {"in": [59899, 22707], "out": [41841]},
        {"in": [13770, 14825], "out": [64606]},
        {"in": [17513, 30720], "out": [39122]}
    ]
}
