{
    "name": "syn_2inp_len3_000318",
    "max_cycles": 32,
    "input_ports": [0, 1],
    "output_ports": [0],
    "tests": [
        {"in": [10687, 23161], "out": [23163]},
        {"in": [41202, 57469], "out": [57471]},
        {"in": [45381, 31920], "out": [31916]},
        {"in": [20991, 40843], "out": [40841]},
        {"in": [52456, 54823], "out": [54821]},
        {"in": [29180, 51689], "out": [51691]},
        {"in": [47931, 9635], "out": [9633]},
        {"in": [38777, 64843], "out": [64841]},
        {"in": [32768, 5], "out": [7]},
        {"in": [19817, 62000], "out": [61996]}
    ]
}
