{
    "name": "syn_1inp_len4_000651",
    "max_cycles": 32,
    "input_ports": [0],
    "output_ports": [0],
    "tests": [
        {"in": [0], "out": [0]},
        {"in": [1], "out": [1]},
        {"in": [18458], "out": [41636]},
        {"in": [50161], "out": [2273]},
        {"in": [61481], "out": [59025]},
        {"in": [27216], "out": [22784]},
        {"in": [57768], "out": [48704]},
        {"in": [64], "out": [4096]},
        {"in": [20602], "out": [31268]},
        {"in": [55639], "out": [39825]}
    ]
}
