{
    "name": "syn_2inp_len6_000320",
    "max_cycles": 32,
    "input_ports": [0, 1],
    "output_ports": [0],
    "tests": [
        {"in": [3080, 3928], "out": [3840]},
        {"in": [32433, 27675], "out": [0]},
        {"in": [23183, 7114], "out": [7116]},
        {"in": [38505, 4707], "out": [4608]},
        {"in": [15, 128], "out": [130]},
        {"in": [42742, 53261], "out": [53248]},
        {"in": [17884, 32346], "out": [32336]},
        {"in": [48408, 5853], "out": [5632]},
        {"in": [15797, 48281], "out": [47104]},
        {"in": [25836, 22064], "out": [22064]}
    ]
}
