{
    "name": "syn_1inp_len5_000443",
    "max_cycles": 32,
    "input_ports": [0],
    "output_ports": [0],
    "tests": [
        {"in": [0], "out": [65528]},
        {"in": [1], "out": [65532]},
        {"in": [65396], "out": [64968]},
        {"in": [50203], "out": [4196]},
        {"in": [47407], "out": [58548]},
        {"in": [50917], "out": [7052]},
        {"in": [32767], "out": [65524]},
        {"in": [3], "out": [4]},
        {"in": [49551], "out": [1588]},
        {"in": [39236], "out": [25864]}
    ]
}
