{
    "name": "syn_2inp_len3_000644",
    "max_cycles": 32,
    "input_ports": [0, 1],
    "output_ports": [0],
    "tests": [
        {"in": [42074, 54823], "out": [54821]},
        {"in": [55788, 62374], "out": [62371]},
        {"in": [9388, 24099], "out": [24097]},
        {"in": [45957, 50010], "out": [50007]},
        {"in": [256, 256], "out": [253]},
        {"in": [49645, 30147], "out": [30145]},
        {"in": [14140, 57107], "out": [57105]},
        {"in": [5674, 32380], "out": [32377]},
        {"in": [44554, 35632], "out": [35629]},
        {"in": [6735, 45153], "out": [45151]}
    ]
}
