{
    "name": "syn_2inp_len4_000194",
    "max_cycles": 32,
    "input_ports": [0, 1],
    "output_ports": [0],
    "tests": [
        {"in": [39823, 15765], "out": [15781]},
        {"in": [5729, 36208], "out": [36224]},
        {"in": [43310, 52646], "out": [52662]},
        {"in": [3349, 40322], "out": [40338]},
        {"in": [44051, 19093], "out": [19109]},
        {"in": [39691, 37178], "out": [37194]},
        {"in": [62127, 6664], "out": [6680]},
        {"in": [32662, 45637], "out": [45653]},
        {"in": [34887, 43973], "out": [43989]},
        {"in": [8, 8], "out": [24]}
    ]
}
