{
    "name": "syn_2inp_len4_000964",
    "max_cycles": 32,
    "input_ports": [0, 1],
    "output_ports": [0],
    "tests": [
        {"in": [44417, 27370], "out": [44422]},
        {"in": [8068, 62019], "out": [8073]},
        {"in": [63873, 3575], "out": [63878]},
        {"in": [40941, 5927], "out": [40946]},
        {"in": [25293, 64300], "out": [25298]},
        {"in": [10211, 27584], "out": [10216]},
        {"in": [16562, 62261], "out": [16567]},
        {"in": [43684, 31553], "out": [43689]},
        {"in": [19913, 10271], "out": [19918]},
        {"in": [7320, 45023], "out": [7325]}
    ]
}
