{
    "name": "syn_2inp_len4_000447",
    "max_cycles": 32,
    "input_ports": [0, 1],
    "output_ports": [0],
    "tests": [
        {"in": [49766, 602], "out": [33994]},
        {"in": [35303, 42476], "out": [5068]},
        {"in": [49525, 53400], "out": [33512]},
        {"in": [39011, 62631], "out": [12484]},
        {"in": [53445, 51512], "out": [41352]},
        {"in": [9530, 2662], "out": [19058]},
        {"in": [54370, 63794], "out": [43202]},
        {"in": [33283, 61818], "out": [1028]},
        {"in": [7339, 61035], "out": [14676]},
        {"in": [19200, 15100], "out": [38398]}
    ]
}
