{
    "name": "syn_2inp_len5_000230",
    "max_cycles": 32,
    "input_ports": [0, 1],
    "output_ports": [0],
    "tests": [
        {"in": [24229, 22273], "out": [60600]},
        {"in": [11101, 45928], "out": [53142]},
        {"in": [64, 64], "out": [0]},
        {"in": [59091, 34910], "out": [8934]},
        {"in": [30450, 62325], "out": [62706]},
        {"in": [5306, 56077], "out": [24722]},
        {"in": [26404, 46240], "out": [22776]},
        {"in": [59741, 36580], "out": [12430]},
        {"in": [13193, 10215], "out": [55076]},
        {"in": [27678, 3006], "out": [12480]}
    ]
}
