{
    "name": "syn_2inp_len4_000655",
    "max_cycles": 32,
    "input_ports": [0, 1],
    "output_ports": [0],
    "tests": [
        {"in": [6608, 26121], "out": [6638]},
        {"in": [8020, 63891], "out": [8042]},
        {"in": [39192, 17899], "out": [39206]},
        {"in": [16474, 445], "out": [16484]},
        {"in": [7, 7], "out": [57]},
        {"in": [48010, 22661], "out": [48052]},
        {"in": [62700, 27040], "out": [62674]},
        {"in": [15466, 35083], "out": [15444]},
        {"in": [30708, 32835], "out": [30666]},
        {"in": [32, 32], "out": [30]}
    ]
}
